{
  "students":[
    {
      "id":"2020-11-03 – 17:03:03",
      "name":"aa",
      "age":11,
      "bio":"a1a1"
    },
    {
      "id":"2020-11-03 – 17:03:12",
      "name":"bb",
      "age":22,
      "bio":"b2b2"
    },
    {
      "id":"2020-11-03 – 17:03:21",
      "name":"cc",
      "age":33,
      "bio":"c3c3"
    },
    {
      "id":"2020-11-03 – 17:06:11",
      "name":"ddd",
      "age":444,
      "bio":"d4d4d4"
    },
    {
      "id":"2020-11-03 – 18:07:23",
      "name":"fff",
      "age":555,
      "bio":"f5f5f5"
    },
    {
      "id":"2020-11-03 – 18:07:38",
      "name":"eeee",
      "age":6666,
      "bio":"e6e6e6"
    },
    {
      "id":"2020-11-03 – 18:07:50",
      "name":"gggg",
      "age":777,
      "bio":"g7g7g7"
    }
  ]
}